{
  "id": 230,
  "url": "https://benyehuda.org/author/230",
  "metadata": {
    "name": "אנדרה אדי",
    "sort_name": "אדי, אנדרה",
    "other_designations": "",
    "intellectual_property": "public_domain",
    "person": {
      "gender": "male",
      "period": null,
      "birth_year": "1877",
      "death_year": "1919"
    },
    "bio_snippet": "היה משורר הונגרי.",
    "languages": [
      "hu"
    ],
    "genres": [
      "poetry"
    ],
    "impressions_count": 15452
  },
  "texts": {
    "author": [
      890,
      1347,
      1658,
      1969,
      2285,
      2598,
      5406,
      5757,
      6050,
      6374,
      6699,
      7027,
      7356,
      7677,
      7994,
      8321,
      8644,
      14045,
      14046,
      14047,
      14048,
      14049,
      14050,
      14051,
      14052,
      14053,
      14054,
      14055,
      14056,
      14057,
      14058,
      14059,
      14060,
      14061,
      14062,
      14063,
      14064,
      14065,
      14066,
      14067,
      14068,
      14069,
      14070,
      14071,
      14072,
      14073,
      14074,
      14075,
      14076,
      14077,
      14078,
      50776,
      50777,
      50778,
      50779,
      50780,
      50781,
      50782,
      50783,
      50784,
      50785,
      50786,
      50787,
      50788,
      50789,
      50790,
      50791,
      50792,
      50793,
      50794,
      50795,
      50796,
      50797,
      50798,
      50799,
      50800,
      50801,
      50802,
      50803,
      50804,
      50805,
      50806,
      50807
    ],
    "editor": [],
    "illustrator": [],
    "translator": [],
    "photographer": [],
    "designer": [],
    "contributor": [],
    "other": []
  },
  "enrichment": {
    "texts_about": []
  }
}